{
    "extensionName": {
        "message": "TabJump - Intelligent Tab Navigator"
    },
    "extensionDescription": {
        "message": "Un nuovo modo per navigare le vostre schede. Accedere facilmente a schede più utilizzati, schede associate, e le schede chiuse. Consente linguetta di bloccaggio troppo."
    },
    "extensionPageActionTitle": {
        "message": "TabJump!"
    },
    "loading": {
        "message": "caricamento..."
    },
    "clickToOpen": {
        "message": "Clicca per aprire \"$title$\"",
        "placeholders": {
            "title": {
                "content": "$1"
            }
        }
    },
    "sureToLeavePage": {
        "message": "Sei sicuro di voler uscire da questa pagina?"
    },
    "jump": {
        "message": "Jump"
    },
    "frequentlyUsedTabs": {
        "message": "Frequently used tabs"
    },
    "undo": {
        "message": "Undo"
    },
    "recentlyClosedTabs": {
        "message": "Recently closed tabs"
    },
    "related": {
        "message": "Related"
    },
    "relatedTabs": {
        "message": "Related tabs"
    },
    "unlockPage": {
        "message": "sbloccare questa pagina"
    },
    "lockPage": {
        "message": "Bloccare questa pagina"
    },
    "cannotLockPage": {
        "message": "Non può bloccare questa pagina"
    }
}
